GoodQuotes-1.0.1.dist-info/DESCRIPTION.rst
GoodQuotes-1.0.1.dist-info/METADATA
GoodQuotes-1.0.1.dist-info/RECORD
GoodQuotes-1.0.1.dist-info/WHEEL
GoodQuotes-1.0.1.dist-info/entry_points.txt
GoodQuotes-1.0.1.dist-info/metadata.json
GoodQuotes-1.0.1.dist-info/top_level.txt
goodquotes/__init__.py
goodquotes/cli.py
goodquotes/logic.py
goodquotes/parser.py
goodquotes/quote.py
