Metadata-Version: 2.0
Name: GoodQuotes
Version: 1.0.1
Summary: UNKNOWN
Home-page: https://github.com/kshitij10496/goodquotes
Author: kshitij10496
Author-email: KshitijSaraogi@gmail.com
License: UNKNOWN
Download-URL: https://github.com/kshitij10496/goodquotes/archive/v1.0.1.tar.gz
Platform: UNKNOWN
Requires-Dist: Click
Requires-Dist: requests
Requires-Dist: bs4
